{
  "id": 67690,
  "created_username": " research.ankit12345@gmail.com, 48",
  "created_ago": "0\u00a0minutes",
  "completed_by": {
    "id": 48,
    "first_name": "",
    "last_name": "",
    "email": "research.ankit12345@gmail.com"
  },
  "task": {
    "id": 4160,
    "data": {
      "data": "/data/local-files/?d=label-studio/data/Images/random_jackets_350_Collar-Style--cutaway_men_jackets--jackets_Collar-Style--cutaway_men_jackets--local--Images--273826241152--1.jpg"
    },
    "meta": {},
    "created_at": "2021-12-13T08:54:14.666028Z",
    "updated_at": "2021-12-13T08:54:14.666070Z",
    "is_labeled": true,
    "overlap": 1,
    "project": 2,
    "file_upload": null
  },
  "result": [
    {
      "value": {
        "choices": [
          "other"
        ]
      },
      "id": "CYhip1PC_W",
      "from_name": "department",
      "to_name": "image",
      "type": "choices"
    }
  ],
  "was_cancelled": false,
  "ground_truth": false,
  "created_at": "2021-12-18T06:54:58.704718Z",
  "updated_at": "2021-12-18T06:54:58.704772Z",
  "lead_time": 4.633
}