{
  "id": 38889,
  "created_username": " research.kamlesh1234@gmail.com, 19",
  "created_ago": "0\u00a0minutes",
  "completed_by": {
    "id": 19,
    "first_name": "",
    "last_name": "",
    "email": "research.kamlesh1234@gmail.com"
  },
  "task": {
    "id": 6945,
    "data": {
      "data": "/data/local-files/?d=label-studio/data/Images/random_jackets_350_Performance-Activity--hunting_men_jackets--jackets_Performance-Activity--hunting_men_jackets--local--Images--115032153327--0.jpg"
    },
    "meta": {},
    "created_at": "2021-12-13T08:56:05.185329Z",
    "updated_at": "2021-12-13T08:56:05.185374Z",
    "is_labeled": true,
    "overlap": 1,
    "project": 3,
    "file_upload": null
  },
  "result": [
    {
      "value": {
        "choices": [
          "jacket"
        ]
      },
      "id": "e2GhXIonGO",
      "from_name": "department",
      "to_name": "image",
      "type": "choices"
    },
    {
      "value": {
        "choices": [
          "Regular/Mid-length"
        ]
      },
      "id": "ZjJLNtSXIt",
      "from_name": "jacket-length",
      "to_name": "image",
      "type": "choices"
    },
    {
      "value": {
        "choices": [
          "Long sleeve"
        ]
      },
      "id": "-23y0NKcih",
      "from_name": "jacket-sleeve-length",
      "to_name": "image",
      "type": "choices"
    },
    {
      "value": {
        "choices": [
          "Solid"
        ]
      },
      "id": "8gz_rFkZj4",
      "from_name": "jacket-pattern",
      "to_name": "image",
      "type": "choices"
    },
    {
      "value": {
        "choices": [
          "Not-Applicable/Visible"
        ]
      },
      "id": "-4g_i2K2pK",
      "from_name": "jacket-style",
      "to_name": "image",
      "type": "choices"
    }
  ],
  "was_cancelled": false,
  "ground_truth": false,
  "created_at": "2021-12-17T04:40:09.649251Z",
  "updated_at": "2021-12-17T04:40:09.649301Z",
  "lead_time": 65.28
}