{
  "id": 41671,
  "created_username": " research.kamlesh1234@gmail.com, 19",
  "created_ago": "0\u00a0minutes",
  "completed_by": {
    "id": 19,
    "first_name": "",
    "last_name": "",
    "email": "research.kamlesh1234@gmail.com"
  },
  "task": {
    "id": 7090,
    "data": {
      "data": "/data/local-files/?d=label-studio/data/Images/random_hoodies_350_Collar-Style--spread_men_hoodies--hoodies_Collar-Style--spread_men_hoodies--local--Images--203556314974--4.jpg"
    },
    "meta": {},
    "created_at": "2021-12-13T08:56:07.584375Z",
    "updated_at": "2021-12-13T08:56:07.584432Z",
    "is_labeled": true,
    "overlap": 1,
    "project": 3,
    "file_upload": null
  },
  "result": [
    {
      "value": {
        "choices": [
          "hoodie"
        ]
      },
      "id": "RbEHl3E9ZH",
      "from_name": "department",
      "to_name": "image",
      "type": "choices"
    },
    {
      "value": {
        "choices": [
          "Regular/Mid-length"
        ]
      },
      "id": "XkSnfd26xc",
      "from_name": "hoodie-length",
      "to_name": "image",
      "type": "choices"
    },
    {
      "value": {
        "choices": [
          "Long sleeve"
        ]
      },
      "id": "cvGsznYOws",
      "from_name": "hoodie-sleeve-length",
      "to_name": "image",
      "type": "choices"
    },
    {
      "value": {
        "choices": [
          "Solid"
        ]
      },
      "id": "fSJqP5zUcQ",
      "from_name": "hoodie-pattern",
      "to_name": "image",
      "type": "choices"
    },
    {
      "value": {
        "choices": [
          "Not-Applicable/Visible"
        ]
      },
      "id": "RMv1_z4xun",
      "from_name": "hoodie-style",
      "to_name": "image",
      "type": "choices"
    }
  ],
  "was_cancelled": false,
  "ground_truth": false,
  "created_at": "2021-12-17T05:56:24.041426Z",
  "updated_at": "2021-12-17T05:56:24.041474Z",
  "lead_time": 30.143
}