{
  "id": 64308,
  "created_username": " research.kamlesh1234@gmail.com, 19",
  "created_ago": "0\u00a0minutes",
  "completed_by": {
    "id": 19,
    "first_name": "",
    "last_name": "",
    "email": "research.kamlesh1234@gmail.com"
  },
  "task": {
    "id": 7844,
    "data": {
      "data": "/data/local-files/?d=label-studio/data/Images/random_jackets_350_Theme--skull_men_jackets--jackets_Theme--skull_men_jackets--local--Images--113976498365--3.jpg"
    },
    "meta": {},
    "created_at": "2021-12-13T08:56:19.274574Z",
    "updated_at": "2021-12-13T08:56:19.274617Z",
    "is_labeled": true,
    "overlap": 1,
    "project": 3,
    "file_upload": null
  },
  "result": [
    {
      "value": {
        "choices": [
          "jacket"
        ]
      },
      "id": "XbZRO7idTO",
      "from_name": "department",
      "to_name": "image",
      "type": "choices"
    },
    {
      "value": {
        "choices": [
          "Regular/Mid-length"
        ]
      },
      "id": "LA0nDGU57X",
      "from_name": "jacket-length",
      "to_name": "image",
      "type": "choices"
    },
    {
      "value": {
        "choices": [
          "Long sleeve"
        ]
      },
      "id": "985nFuMpx0",
      "from_name": "jacket-sleeve-length",
      "to_name": "image",
      "type": "choices"
    },
    {
      "value": {
        "choices": [
          "Herringbone/Flecked"
        ]
      },
      "id": "ORuFM1qyjW",
      "from_name": "jacket-pattern",
      "to_name": "image",
      "type": "choices"
    },
    {
      "value": {
        "choices": [
          "Not-Applicable/Visible"
        ]
      },
      "id": "lLfJTZayT2",
      "from_name": "jacket-style",
      "to_name": "image",
      "type": "choices"
    }
  ],
  "was_cancelled": false,
  "ground_truth": false,
  "created_at": "2021-12-18T05:53:53.708182Z",
  "updated_at": "2021-12-18T05:53:53.708234Z",
  "lead_time": 19.957
}