{
  "id": 75774,
  "created_username": " research.kamlesh1234@gmail.com, 19",
  "created_ago": "0\u00a0minutes",
  "completed_by": {
    "id": 19,
    "first_name": "",
    "last_name": "",
    "email": "research.kamlesh1234@gmail.com"
  },
  "task": {
    "id": 8194,
    "data": {
      "data": "/data/local-files/?d=label-studio/data/Images/random_hoodies_350_Knit-Style--waffle-knit_men_hoodies--hoodies_Knit-Style--waffle-knit_men_hoodies--local--Images--203638360021--0.jpg"
    },
    "meta": {},
    "created_at": "2021-12-13T08:56:25.167592Z",
    "updated_at": "2021-12-13T08:56:25.167674Z",
    "is_labeled": true,
    "overlap": 1,
    "project": 3,
    "file_upload": null
  },
  "result": [
    {
      "value": {
        "choices": [
          "hoodie"
        ]
      },
      "id": "Cvgzec_LJs",
      "from_name": "department",
      "to_name": "image",
      "type": "choices"
    },
    {
      "value": {
        "choices": [
          "Regular/Mid-length"
        ]
      },
      "id": "MmHEoAxYG9",
      "from_name": "hoodie-length",
      "to_name": "image",
      "type": "choices"
    },
    {
      "value": {
        "choices": [
          "Long sleeve"
        ]
      },
      "id": "Ue8y7FCDUY",
      "from_name": "hoodie-sleeve-length",
      "to_name": "image",
      "type": "choices"
    },
    {
      "value": {
        "choices": [
          "Striped/Pinstripe"
        ]
      },
      "id": "XLGrGgP6Vo",
      "from_name": "hoodie-pattern",
      "to_name": "image",
      "type": "choices"
    },
    {
      "value": {
        "choices": [
          "Henley/Pullover"
        ]
      },
      "id": "Rj5FPPehTs",
      "from_name": "hoodie-style",
      "to_name": "image",
      "type": "choices"
    }
  ],
  "was_cancelled": false,
  "ground_truth": false,
  "created_at": "2021-12-18T10:02:57.424304Z",
  "updated_at": "2021-12-18T10:02:57.424356Z",
  "lead_time": 24.677
}